password_generator/__init__.py
password_generator/password_generator.py
tests/__init__.py
tests/test_password_generator.py
ete_pass-1.0.2.dist-info/METADATA
ete_pass-1.0.2.dist-info/WHEEL
ete_pass-1.0.2.dist-info/entry_points.txt
ete_pass-1.0.2.dist-info/top_level.txt
ete_pass-1.0.2.dist-info/RECORD
