Metadata-Version: 2.1
Name: ete_pass
Version: 1.0.2
Summary: A strong password generator with choosable characters and length
Home-page: https://github.com/AlirezaEtezad/Password_Generator
Author: Alireza Etezad
Author-email: ar_etezad@yahoo.com
Classifier: Programming Language :: Python :: 3
Classifier: License :: OSI Approved :: MIT License
Classifier: Operating System :: OS Independent
Requires-Python: >=3.6
Requires-Dist: click
